{
  "statistics": {
    "feature_idx": 3626,
    "num_samples": 50,
    "max_activation": 14.536242485046387,
    "mean_activation": 13.061640968322754,
    "std_activation": 0.5999327712074985,
    "min_activation": 12.118535995483398,
    "activation_count": 1053,
    "all_time_max": 14.536242485046387
  },
  "top_samples": [
    {
      "feature_idx": 3626,
      "activation_value": 14.536242485046387,
      "tokens": [
        576,
        573
      ],
      "text": " of the",
      "position": 18,
      "context_tokens": [
        235290,
        1448,
        2952,
        12039,
        674,
        5499,
        22660,
        576,
        573,
        10742,
        50908,
        708,
        15917,
        41660,
        577,
        674,
        5612
      ],
      "context_text": "- We cannot assume that click speakers of the African Southwest are necessarily indigenous to that region"
    },
    {
      "feature_idx": 3626,
      "activation_value": 14.270645141601562,
      "tokens": [
        8517,
        577
      ],
      "text": "forts to",
      "position": 3,
      "context_tokens": [
        2,
        57135,
        8517,
        577,
        39305,
        89684,
        40311,
        685,
        476,
        66447,
        12414,
        685
      ],
      "context_text": "<bos>Efforts to incorporate Bowmanstown as a borough occurred as"
    },
    {
      "feature_idx": 3626,
      "activation_value": 14.074666976928711,
      "tokens": [
        573,
        7757
      ],
      "text": " the Association",
      "position": 11,
      "context_tokens": [
        235284,
        235276,
        235274,
        235284,
        9771,
        12028,
        731,
        573,
        7757,
        604,
        7040,
        111213,
        35889,
        1942,
        235248,
        235308,
        235284
      ],
      "context_text": "2012 survey conducted by the Association for Pet Obesity Prevention found 52"
    },
    {
      "feature_idx": 3626,
      "activation_value": 14.073151588439941,
      "tokens": [
        235276,
        235274
      ],
      "text": "01",
      "position": 5,
      "context_tokens": [
        2,
        235280,
        235248,
        235284,
        235276,
        235274,
        235284,
        9771,
        12028,
        731,
        573,
        7757,
        604,
        7040
      ],
      "context_text": "<bos>A 2012 survey conducted by the Association for Pet"
    },
    {
      "feature_idx": 3626,
      "activation_value": 14.038758277893066,
      "tokens": [
        731,
        573
      ],
      "text": " by the",
      "position": 10,
      "context_tokens": [
        235248,
        235284,
        235276,
        235274,
        235284,
        9771,
        12028,
        731,
        573,
        7757,
        604,
        7040,
        111213,
        35889,
        1942,
        235248,
        235308
      ],
      "context_text": " 2012 survey conducted by the Association for Pet Obesity Prevention found 5"
    },
    {
      "feature_idx": 3626,
      "activation_value": 14.018379211425781,
      "tokens": [
        1297,
        2377
      ],
      "text": " only point",
      "position": 4,
      "context_tokens": [
        2,
        235285,
        877,
        1297,
        2377,
        921,
        1378,
        212297,
        235292,
        108,
        235290,
        1448,
        2952
      ],
      "context_text": "<bos>I will only point out two caveats:\n- We cannot"
    },
    {
      "feature_idx": 3626,
      "activation_value": 13.958168029785156,
      "tokens": [
        7757,
        604
      ],
      "text": " Association for",
      "position": 12,
      "context_tokens": [
        235276,
        235274,
        235284,
        9771,
        12028,
        731,
        573,
        7757,
        604,
        7040,
        111213,
        35889,
        1942,
        235248,
        235308,
        235284,
        235265
      ],
      "context_text": "012 survey conducted by the Association for Pet Obesity Prevention found 52."
    },
    {
      "feature_idx": 3626,
      "activation_value": 13.940896987915039,
      "tokens": [
        12039,
        674
      ],
      "text": " assume that",
      "position": 14,
      "context_tokens": [
        1378,
        212297,
        235292,
        108,
        235290,
        1448,
        2952,
        12039,
        674,
        5499,
        22660,
        576,
        573,
        10742,
        50908,
        708,
        15917
      ],
      "context_text": " two caveats:\n- We cannot assume that click speakers of the African Southwest are necessarily"
    },
    {
      "feature_idx": 3626,
      "activation_value": 13.772798538208008,
      "tokens": [
        573,
        10742
      ],
      "text": " the African",
      "position": 19,
      "context_tokens": [
        1448,
        2952,
        12039,
        674,
        5499,
        22660,
        576,
        573,
        10742,
        50908,
        708,
        15917,
        41660,
        577,
        674,
        5612,
        235269
      ],
      "context_text": " We cannot assume that click speakers of the African Southwest are necessarily indigenous to that region,"
    },
    {
      "feature_idx": 3626,
      "activation_value": 13.768198013305664,
      "tokens": [
        1178,
        4442
      ],
      "text": " than six",
      "position": 13,
      "context_tokens": [
        235248,
        235274,
        235315,
        235308,
        235274,
        235269,
        978,
        1178,
        4442,
        1658,
        1452,
        573,
        1580,
        576,
        3855,
        4143,
        2515
      ],
      "context_text": " 1951, more than six years after the end of World War II"
    },
    {
      "feature_idx": 3626,
      "activation_value": 13.510343551635742,
      "tokens": [
        728,
        692
      ],
      "text": " - you",
      "position": 3,
      "context_tokens": [
        2,
        5546,
        728,
        692,
        2613,
        1938,
        577,
        169518,
        692,
        4544,
        235265,
        5881
      ],
      "context_text": "<bos>First - you might want to redefine you search. Are"
    },
    {
      "feature_idx": 3626,
      "activation_value": 13.473957061767578,
      "tokens": [
        921,
        1378
      ],
      "text": " out two",
      "position": 6,
      "context_tokens": [
        2,
        235285,
        877,
        1297,
        2377,
        921,
        1378,
        212297,
        235292,
        108,
        235290,
        1448,
        2952,
        12039,
        674
      ],
      "context_text": "<bos>I will only point out two caveats:\n- We cannot assume that"
    },
    {
      "feature_idx": 3626,
      "activation_value": 13.334702491760254,
      "tokens": [
        8172,
        235290
      ],
      "text": " jack-",
      "position": 3,
      "context_tokens": [
        2,
        235280,
        8172,
        235290,
        235253,
        19708,
        233631,
        235269,
        974,
        576,
        573,
        22013
      ],
      "context_text": "<bos>A jack-o'-lantern, one of the symbols"
    },
    {
      "feature_idx": 3626,
      "activation_value": 13.32622241973877,
      "tokens": [
        235274,
        235284
      ],
      "text": "12",
      "position": 6,
      "context_tokens": [
        2,
        235280,
        235248,
        235284,
        235276,
        235274,
        235284,
        9771,
        12028,
        731,
        573,
        7757,
        604,
        7040,
        111213
      ],
      "context_text": "<bos>A 2012 survey conducted by the Association for Pet Obesity"
    },
    {
      "feature_idx": 3626,
      "activation_value": 13.308328628540039,
      "tokens": [
        235315,
        235308
      ],
      "text": "95",
      "position": 8,
      "context_tokens": [
        2,
        2122,
        736,
        1744,
        575,
        235248,
        235274,
        235315,
        235308,
        235274,
        235269,
        978,
        1178,
        4442,
        1658,
        1452,
        573
      ],
      "context_text": "<bos>On this day in 1951, more than six years after the"
    },
    {
      "feature_idx": 3626,
      "activation_value": 13.238116264343262,
      "tokens": [
        235356,
        741
      ],
      "text": "Xant",
      "position": 2,
      "context_tokens": [
        2,
        235356,
        741,
        8206,
        16690,
        603,
        476,
        2983,
        495,
        576,
        32962
      ],
      "context_text": "<bos>Xantusiidae is a clade of vivi"
    },
    {
      "feature_idx": 3626,
      "activation_value": 13.225865364074707,
      "tokens": [
        877,
        1297
      ],
      "text": " will only",
      "position": 3,
      "context_tokens": [
        2,
        235285,
        877,
        1297,
        2377,
        921,
        1378,
        212297,
        235292,
        108,
        235290,
        1448
      ],
      "context_text": "<bos>I will only point out two caveats:\n- We"
    },
    {
      "feature_idx": 3626,
      "activation_value": 13.207511901855469,
      "tokens": [
        12028,
        731
      ],
      "text": " conducted by",
      "position": 9,
      "context_tokens": [
        235280,
        235248,
        235284,
        235276,
        235274,
        235284,
        9771,
        12028,
        731,
        573,
        7757,
        604,
        7040,
        111213,
        35889,
        1942,
        235248
      ],
      "context_text": "A 2012 survey conducted by the Association for Pet Obesity Prevention found "
    },
    {
      "feature_idx": 3626,
      "activation_value": 13.156009674072266,
      "tokens": [
        235290,
        1448
      ],
      "text": "- We",
      "position": 11,
      "context_tokens": [
        1297,
        2377,
        921,
        1378,
        212297,
        235292,
        108,
        235290,
        1448,
        2952,
        12039,
        674,
        5499,
        22660,
        576,
        573,
        10742
      ],
      "context_text": " only point out two caveats:\n- We cannot assume that click speakers of the African"
    },
    {
      "feature_idx": 3626,
      "activation_value": 13.146039009094238,
      "tokens": [
        1938,
        577
      ],
      "text": " want to",
      "position": 6,
      "context_tokens": [
        2,
        5546,
        728,
        692,
        2613,
        1938,
        577,
        169518,
        692,
        4544,
        235265,
        5881,
        692,
        3648,
        604
      ],
      "context_text": "<bos>First - you might want to redefine you search. Are you looking for"
    }
  ]
}